{
  "_class": "group",
  "do_objectID": "8919F44F-0CE4-4115-97E2-9C79DF17BD5F",
  "exportOptions": {
    "_class": "exportOptions",
    "exportFormats": [
    ],
    "includedLayerIds": [
    ],
    "layerOptions": 0,
    "shouldTrim": false
  },
  "frame": {
    "_class": "rect",
    "constrainProportions": false,
    "height": 90,
    "width": 24,
    "x": 541.1379310344828,
    "y": 148
  },
  "hasClickThrough": false,
  "isFlippedHorizontal": false,
  "isFlippedVertical": false,
  "isLocked": false,
  "isVisible": true,
  "layerListExpandedType": 0,
  "layers": [
    {
      "class": "shapeGroup",
      "id": "7A47050D-129B-461B-9B2A-9CD06E7783F6"
    },
    {
      "class": "text",
      "id": "03584186-1FE6-4A91-899F-660E6D362E6A"
    },
    {
      "class": "shapeGroup",
      "id": "3815DB3E-9B47-49A1-B2B8-24E3156DB2F5"
    }
  ],
  "name": "Group 63 Copy 22",
  "nameIsFixed": false,
  "resizingConstraint": 9,
  "resizingType": 0,
  "rotation": 0,
  "shouldBreakMaskChain": false,
  "style": {
    "_class": "style",
    "endDecorationType": 0,
    "miterLimit": 10,
    "startDecorationType": 0
  }
}