{
  "_class": "group",
  "do_objectID": "CB3CAED0-5B42-48B4-9EA4-EEC794B13B24",
  "exportOptions": {
    "_class": "exportOptions",
    "exportFormats": [
    ],
    "includedLayerIds": [
    ],
    "layerOptions": 0,
    "shouldTrim": false
  },
  "frame": {
    "_class": "rect",
    "constrainProportions": false,
    "height": 83,
    "width": 31,
    "x": 901,
    "y": 227
  },
  "hasClickThrough": false,
  "isFlippedHorizontal": false,
  "isFlippedVertical": false,
  "isLocked": false,
  "isVisible": true,
  "layerListExpandedType": 0,
  "layers": [
    {
      "class": "shapeGroup",
      "id": "6095694B-E594-4E10-A0B0-381B1307ED63"
    },
    {
      "class": "text",
      "id": "27F1A029-C669-453D-830F-A4B7FC428E43"
    },
    {
      "class": "shapeGroup",
      "id": "DD140260-D649-45F9-B045-90267AD47DE6"
    }
  ],
  "name": "Group 63 Copy",
  "nameIsFixed": false,
  "resizingConstraint": 9,
  "resizingType": 0,
  "rotation": 0,
  "shouldBreakMaskChain": false,
  "style": {
    "_class": "style",
    "endDecorationType": 0,
    "miterLimit": 10,
    "startDecorationType": 0
  }
}