{
  "_class": "group",
  "do_objectID": "C71C916A-3ACA-45F9-8E40-48B38993EEF6",
  "exportOptions": {
    "_class": "exportOptions",
    "exportFormats": [
    ],
    "includedLayerIds": [
    ],
    "layerOptions": 0,
    "shouldTrim": false
  },
  "frame": {
    "_class": "rect",
    "constrainProportions": false,
    "height": 12,
    "width": 46,
    "x": 646,
    "y": 266
  },
  "hasClickThrough": false,
  "isFlippedHorizontal": false,
  "isFlippedVertical": false,
  "isLocked": false,
  "isVisible": true,
  "layerListExpandedType": 2,
  "layers": [
    {
      "class": "text",
      "id": "32C0C081-3C15-4E03-8048-992A976481CD"
    },
    {
      "class": "shapeGroup",
      "id": "5943D9A3-2DEE-4060-8C74-F2E8CBC1A6A4"
    }
  ],
  "name": "Group Copy",
  "nameIsFixed": false,
  "resizingConstraint": 63,
  "resizingType": 0,
  "rotation": 0,
  "shouldBreakMaskChain": false,
  "style": {
    "_class": "style",
    "endDecorationType": 0,
    "miterLimit": 10,
    "startDecorationType": 0
  }
}