{
  "_class": "shapeGroup",
  "clippingMaskMode": 0,
  "do_objectID": "98D3D2F1-A236-4ECA-A5E9-470314127148",
  "exportOptions": {
    "_class": "exportOptions",
    "exportFormats": [
    ],
    "includedLayerIds": [
    ],
    "layerOptions": 0,
    "shouldTrim": false
  },
  "frame": {
    "_class": "rect",
    "constrainProportions": false,
    "height": 24,
    "width": 72,
    "x": 210,
    "y": 104
  },
  "hasClickThrough": false,
  "hasClippingMask": false,
  "isFlippedHorizontal": false,
  "isFlippedVertical": false,
  "isLocked": false,
  "isVisible": true,
  "layerListExpandedType": 0,
  "layers": [
    {
      "class": "rectangle",
      "id": "C2C66CEF-4612-4033-80CE-CB97EE214D90"
    }
  ],
  "name": "button bg copy 2",
  "nameIsFixed": true,
  "resizingConstraint": 63,
  "resizingType": 0,
  "rotation": 0,
  "shouldBreakMaskChain": false,
  "style": {
    "sharedObjectID": "B53ED5EF-9B26-4F37-A6A4-2BA28661124A"
  },
  "windingRule": 1
}